atoti_aws/__init__.py
atoti_aws/_plugin.py
atoti_aws/_s3_ping_discovery_protocol.py
atoti_aws/client_side_encryption/__init__.py
atoti_aws/client_side_encryption/_client_side_encryption.py
atoti_aws/client_side_encryption/key_pair.py
atoti_aws/client_side_encryption/kms_config.py
atoti_aws/data/atoti-aws.jar
atoti_aws/py.typed
atoti_aws-0.8.14.dist-info/METADATA
atoti_aws-0.8.14.dist-info/WHEEL
atoti_aws-0.8.14.dist-info/entry_points.txt
atoti_aws-0.8.14.dist-info/RECORD
